spider/__init__.py
spider/bibtex.py
spider/constants.py
spider/convert.py
spider/objects.py
spider/protocols.conf
spider/spider_logo.png
spider/utils.py
spider/wizards.py
spider/protocols/__init__.py
spider/protocols/protocol_align_apsr.py
spider/protocols/protocol_align_base.py
spider/protocols/protocol_align_pairwise.py
spider/protocols/protocol_base.py
spider/protocols/protocol_ca_pca.py
spider/protocols/protocol_classify_base.py
spider/protocols/protocol_classify_diday.py
spider/protocols/protocol_classify_kmeans.py
spider/protocols/protocol_classify_ward.py
spider/protocols/protocol_custommask.py
spider/protocols/protocol_filters.py
spider/protocols/protocol_projmatch.py
spider/protocols/protocol_reconstruct.py
spider/scripts/cp_endian.spi
spider/scripts/26.06/recons_fourier.txt
spider/scripts/26.06/mda/apsr4class.msa
spider/scripts/26.06/mda/ca-pca.msa
spider/scripts/26.06/mda/center1.msa
spider/scripts/26.06/mda/classavg.msa
spider/scripts/26.06/mda/cluster.msa
spider/scripts/26.06/mda/custommask.msa
spider/scripts/26.06/mda/hierarchical.msa
spider/scripts/26.06/mda/kmeans.msa
spider/scripts/26.06/mda/pairwise.msa
spider/scripts/26.06/mpi/bp-32f.mpi
spider/scripts/26.06/mpi/bp-3f.mpi
spider/scripts/26.06/projmatch/Refinement/defocus-groups/endmerge.pam
spider/scripts/26.06/projmatch/Refinement/defocus-groups/endrefine.pam
spider/scripts/26.06/projmatch/Refinement/defocus-groups/enhance.pam
spider/scripts/26.06/projmatch/Refinement/defocus-groups/grploop.pam
spider/scripts/26.06/projmatch/Refinement/defocus-groups/mergegroups.pam
spider/scripts/26.06/projmatch/Refinement/defocus-groups/prepare.pam
spider/scripts/26.06/projmatch/Refinement/defocus-groups/refine.pam
spider/scripts/26.06/projmatch/Refinement/defocus-groups/refine_settings.pam
spider/scripts/26.06/projmatch/Refinement/defocus-groups/smangloop.pam
spider/scripts/26.06/projmatch/Refinement/no-defocus-groups/enhance.pam
spider/scripts/26.06/projmatch/Refinement/no-defocus-groups/merge-fsc-filt.pam
scipion_em_spider-3.1.8.dist-info/LICENSE
scipion_em_spider-3.1.8.dist-info/METADATA
scipion_em_spider-3.1.8.dist-info/WHEEL
scipion_em_spider-3.1.8.dist-info/entry_points.txt
scipion_em_spider-3.1.8.dist-info/top_level.txt
scipion_em_spider-3.1.8.dist-info/RECORD
